{   
    "articles": [
        {
            "title": "Educating in a New World",
            "text": "I had the great opportunity to sit down and have an awesome conversation with First Grade Teacher Daniel Noles about what life is like teaching virtually from home. He shared some of the challenges and roadblocks and how this may impact our children for years to come. Hope you enjoy it!",
            "date": "1/20/2021"
        },
        {
            "title": "",
            "text": "You're all caught up!",
            "date": ""
        }
    ]
}